nsta_assistant/__init__.py
nsta_assistant/main.py
nsta_assistant/classes/classes.py
nsta_assistant/classes/exceptions.py
nsta_assistant/utils/handler.py
nsta_assistant/utils/utils.py
tests/tests.py
nsta_assistant-0.0.12.dist-info/LICENSE
nsta_assistant-0.0.12.dist-info/METADATA
nsta_assistant-0.0.12.dist-info/WHEEL
nsta_assistant-0.0.12.dist-info/entry_points.txt
nsta_assistant-0.0.12.dist-info/top_level.txt
nsta_assistant-0.0.12.dist-info/RECORD
